sigmaeval/__init__.py
sigmaeval/sigmaeval.py
sigmaeval-0.1.0.dist-info/LICENSE
sigmaeval-0.1.0.dist-info/METADATA
sigmaeval-0.1.0.dist-info/WHEEL
sigmaeval-0.1.0.dist-info/top_level.txt
sigmaeval-0.1.0.dist-info/RECORD
