Metadata-Version: 2.2
Name: sigmaeval
Version: 0.1.0
Summary: Evaluation metrics for probabilistic and quantile predictions including CRPS, Brier score, and other uncertainty quantification metrics.
Home-page: https://github.com/sebhaan/sigmaeval
Author: Sebastian Haan
Classifier: Programming Language :: Python :: 3
Classifier: License :: OSI Approved :: Apache Software License
Classifier: Operating System :: OS Independent
Requires-Python: >=3.9
License-File: LICENSE
Requires-Dist: numpy>=1.21
Requires-Dist: pytest>=8.0
Dynamic: author
Dynamic: classifier
Dynamic: description
Dynamic: description-content-type
Dynamic: home-page
Dynamic: requires-dist
Dynamic: requires-python
Dynamic: summary
